<?xml version="1.0" encoding="utf-8"?>
<odoo>

    <!-- Imports submenu -->
    <menuitem id="menu_federation_imports"
              name="Imports &amp; Integrations"
              parent="sports_federation_base.menu_federation_administration"
              sequence="10"/>

    <!-- Import Clubs -->
    <menuitem id="menu_federation_import_clubs"
              name="Import Clubs"
              parent="menu_federation_imports"
              action="action_federation_import_clubs_wizard"
              sequence="10"/>

    <!-- Import Seasons -->
    <menuitem id="menu_federation_import_seasons"
              name="Import Seasons"
              parent="menu_federation_imports"
              action="action_federation_import_seasons_wizard"
              sequence="20"/>

    <!-- Import Players -->
    <menuitem id="menu_federation_import_players"
              name="Import Players"
              parent="menu_federation_imports"
              action="action_federation_import_players_wizard"
              sequence="30"/>

    <!-- Import Teams -->
    <menuitem id="menu_federation_import_teams"
              name="Import Teams"
              parent="menu_federation_imports"
              action="action_federation_import_teams_wizard"
              sequence="40"/>

    <!-- Import Tournament Participants -->
    <menuitem id="menu_federation_import_tournament_participants"
              name="Import Tournament Participants"
              parent="menu_federation_imports"
              action="action_federation_import_tournament_participants_wizard"
              sequence="50"/>

    <menuitem id="menu_federation_import_jobs"
              name="Import Governance Jobs"
              parent="menu_federation_imports"
              action="action_federation_import_jobs"
              sequence="60"/>

    <menuitem id="menu_federation_import_templates"
              name="Import Templates"
              parent="menu_federation_imports"
              action="action_federation_import_templates"
              sequence="70"
              groups="sports_federation_base.group_federation_manager"/>

    <menuitem id="menu_federation_integration_contracts"
              name="Integration Contracts"
              parent="menu_federation_imports"
              action="action_federation_integration_contracts"
              sequence="80"
              groups="sports_federation_base.group_federation_manager"/>

    <menuitem id="menu_federation_integration_partners"
              name="Integration Partners"
              parent="menu_federation_imports"
              action="action_federation_integration_partners"
              sequence="90"
              groups="sports_federation_base.group_federation_manager"/>

    <menuitem id="menu_federation_integration_deliveries"
              name="Inbound Deliveries"
              parent="menu_federation_imports"
              action="action_federation_integration_deliveries"
              sequence="100"
              groups="sports_federation_base.group_federation_manager"/>

</odoo>